setup.py
src/unittestextras/DataProvider.py
src/unittestextras/DataProviderSingleton.py
src/unittestextras/DataSet.py
src/unittestextras/DataSource.py
src/unittestextras/__init__.py
src/unittestextras.egg-info/PKG-INFO
src/unittestextras.egg-info/SOURCES.txt
src/unittestextras.egg-info/dependency_links.txt
src/unittestextras.egg-info/top_level.txt
test/test_DataProvider.py
test/test_DataProviderSingleton.py
test/test_DataSource.py