Metadata-Version: 1.0
Name: unittestextras
Version: 1.0
Summary: Extra Unittest Functionality
Home-page: https://github.com/sharonlev/pyUnittestExtras
Author: Sharon Lev
Author-email: sharon_lev@yahoo.com
License:                     GNU GENERAL PUBLIC LICENSE
